django_deprecated_field/__init__.py
django_deprecated_field/deprecated_field.py
django_deprecated_field-0.1.1.dist-info/METADATA
django_deprecated_field-0.1.1.dist-info/WHEEL
django_deprecated_field-0.1.1.dist-info/licenses/LICENSE
django_deprecated_field-0.1.1.dist-info/RECORD
