Metadata-Version: 2.4
Name: django-deprecated-field
Version: 0.1.1
Summary: Util for marking Django DB fields as deprecated, enabling migration consistency with rolling deploys
Project-URL: Homepage, https://github.com/kolonialno/django-deprecated-field
Project-URL: Bug Tracker, https://github.com/kolonialno/django-deprecated-field/issues
Author-email: Oda Tech <tech@oda.com>
License-File: LICENSE
Classifier: Framework :: Django
Classifier: Framework :: Django :: 4
Classifier: Framework :: Django :: 5
Classifier: Framework :: Django :: 6
Classifier: License :: OSI Approved :: MIT License
Classifier: Operating System :: OS Independent
Classifier: Programming Language :: Python :: 3
Classifier: Programming Language :: Python :: 3.12
Classifier: Programming Language :: Python :: 3.13
Classifier: Programming Language :: Python :: 3.14
Requires-Python: >=3.12
Requires-Dist: django<7.0,>=4.2
